message_protocol/__init__.py
message_protocol/core/__init__.py
message_protocol/core/protocol.py
messageproto-0.1.0.dist-info/METADATA
messageproto-0.1.0.dist-info/WHEEL
messageproto-0.1.0.dist-info/top_level.txt
messageproto-0.1.0.dist-info/RECORD
