Metadata-Version: 2.4
Name: MessageProto
Version: 0.1.0
Summary: A simple messaging protocol written on top of TCP using sockets
Author-email: Raj Adhikari <adhikarirajj07@gmail.com>
Project-URL: GitHub, https://github.com/r-adhikari97
Project-URL: LinkedIn, https://www.linkedin.com/in/adhikari-raj/
Requires-Python: >=3.9
